disqust/__init__.py
disqust-0.1.0.dist-info/DESCRIPTION.rst
disqust-0.1.0.dist-info/METADATA
disqust-0.1.0.dist-info/RECORD
disqust-0.1.0.dist-info/WHEEL
disqust-0.1.0.dist-info/metadata.json
disqust-0.1.0.dist-info/top_level.txt
