Metadata-Version: 2.0
Name: disqust
Version: 0.1.0
Summary: Disqus API client
Home-page: http://github.com/chbrown/disqust-python
Author: Christopher Brown
Author-email: io@henrian.com
License: MIT
Platform: UNKNOWN
Classifier: Development Status :: 3 - Alpha
Classifier: Intended Audience :: Developers
Classifier: License :: OSI Approved :: MIT License
Classifier: Programming Language :: Python
Classifier: Programming Language :: Python :: 2.7
Classifier: Topic :: Communications :: Chat
Classifier: Topic :: Internet :: WWW/HTTP
Classifier: Topic :: Software Development :: Libraries
